[
  { "name": "Jyoti Sinha", "department": "APPLIED SCIENCE" },
  { "name": "Savita Agarwal", "department": "APPLIED SCIENCE" },
  { "name": "Anil Kumar", "department": "APPLIED SCIENCE" },
  { "name": "Manoj Kumar Singh", "department": "APPLIED SCIENCE" },
  { "name": "Pradeep Kumar", "department": "APPLIED SCIENCE" },
  { "name": "Sandeep Kumar", "department": "APPLIED SCIENCE" },
  { "name": "Sanjeev Sharma", "department": "APPLIED SCIENCE" },
  { "name": "Navin Kumar", "department": "APPLIED SCIENCE" },
  { "name": "Ram Bharat Singh", "department": "APPLIED SCIENCE" },
  { "name": "Sachi Singh", "department": "APPLIED SCIENCE" },
  { "name": "Sarita Devi Sharma", "department": "APPLIED SCIENCE" },
  { "name": "Milan Chakarborty", "department": "APPLIED SCIENCE" },
  { "name": "Hema Rani", "department": "APPLIED SCIENCE" },
  { "name": "Vinita Rani", "department": "APPLIED SCIENCE" },
  { "name": "Soma Das", "department": "APPLIED SCIENCE" },
  { "name": "Kamna Sharma", "department": "APPLIED SCIENCE" },
  { "name": "Mohit Arya", "department": "APPLIED SCIENCE" },
  { "name": "Pankaj Kumar", "department": "APPLIED SCIENCE" },
  { "name": "Anjul Sharma", "department": "APPLIED SCIENCE" },
  { "name": "Sourabh Maheshwari", "department": "APPLIED SCIENCE" },
  { "name": "Rajni Dixit", "department": "APPLIED SCIENCE" },
  { "name": "Saurabh Kumar", "department": "APPLIED SCIENCE" },
  { "name": "Purnima Pandey", "department": "APPLIED SCIENCE" },
  { "name": "Veenita Sharma", "department": "APPLIED SCIENCE" },
  { "name": "Adesh Kumar", "department": "APPLIED SCIENCE" },
  { "name": "Kanika Goel", "department": "APPLIED SCIENCE" },
  { "name": "Pearl Goel", "department": "APPLIED SCIENCE" },
  { "name": "Sakshi Puri Goswami", "department": "APPLIED SCIENCE" },
  { "name": "Shivangi Goswami", "department": "APPLIED SCIENCE" },
  { "name": "Shivi Tiwari", "department": "APPLIED SCIENCE" },
  { "name": "Sonika", "department": "APPLIED SCIENCE" },
  { "name": "Ankit Kumar", "department": "APPLIED SCIENCE" },
  { "name": "Sakshi Bansal", "department": "APPLIED SCIENCE" },
  { "name": "Shalini Singh", "department": "APPLIED SCIENCE" },

  { "name": "Ajay Kumar Sharma", "department": "BIOTECHNOLOGY" },
  { "name": "Siddharth Vats", "department": "BIOTECHNOLOGY" },
  { "name": "Shomini Parashar", "department": "BIOTECHNOLOGY" },
  { "name": "Indu Bhatt", "department": "BIOTECHNOLOGY" },
  { "name": "Nikhil Kawatra", "department": "BIOTECHNOLOGY" },
  { "name": "Rabab Anjum", "department": "BIOTECHNOLOGY" },
  { "name": "Manish Pant", "department": "BIOTECHNOLOGY" },
  { "name": "Shweta Kalia", "department": "BIOTECHNOLOGY" },
  { "name": "Rashmi Chandra", "department": "BIOTECHNOLOGY" },

  { "name": "Sonia Juneja", "department": "CS" },
  { "name": "Amit Sharma", "department": "CS" },
  { "name": "Shalendra Kumar", "department": "CS" },
  { "name": "Awdhesh Kumar", "department": "CS" },
  { "name": "Monika Nagar", "department": "CS" },
  { "name": "Sanjeev Sanyal", "department": "CS" },
  { "name": "Dheerendra Kumar Tyagi", "department": "CS" },
  { "name": "Gaurav Bhatia", "department": "CS" },
  { "name": "Shiv Prakash Nath Tripathi", "department": "CS" },
  { "name": "Karan Verma", "department": "CS" },
  { "name": "Shruti Gaur", "department": "CS" },
  { "name": "Hunny Gaur", "department": "CS" },
  { "name": "Kajal Kaushal", "department": "CS" },
  { "name": "Govind Kumar Rahul", "department": "CS" },
  { "name": "Mayank Parashar", "department": "CS" },
  { "name": "Ankita Raj", "department": "CS" },
  { "name": "Amit", "department": "CS" },
  { "name": "Ravi Kumar Dabas", "department": "CS" },
  { "name": "Nadeem Anwar", "department": "CS" },

  { "name": "Sonali Mathur", "department": "CSE" },
  { "name": "Prabhat Kumar Srivastava", "department": "CSE" },
  { "name": "Amit Chugh", "department": "CSE" },
  { "name": "Meenu Sharma", "department": "CSE" },
  { "name": "Nizam Uddin Khan", "department": "CSE" },
  { "name": "Atul Kumar", "department": "CSE" },
  { "name": "Vivek Jain", "department": "CSE" },
  { "name": "Ramesh Kumar Verma", "department": "CSE" },
  { "name": "Saurabh Dwivedi", "department": "CSE" },
  { "name": "Basudeo Singh Roohani", "department": "CSE" },
  { "name": "Pankaj Kumar", "department": "CSE" },
  { "name": "Vibhor Harit", "department": "CSE" },
  { "name": "Anubhav Sharma", "department": "CSE" },
  { "name": "Manoj Kumar Singh", "department": "CSE" },
  { "name": "Mayuri Kulshreshtha", "department": "CSE" },
  { "name": "Monika Belwal", "department": "CSE" },
  { "name": "Nishant Anand", "department": "CSE" },
  { "name": "Pankaj Pratap Singh", "department": "CSE" },
  { "name": "Pooja Tomer", "department": "CSE" },
  { "name": "Ravikant", "department": "CSE" },
  { "name": "Shanu Priya Chauhan", "department": "CSE" },
  { "name": "Vaishali Bhargava", "department": "CSE" },
  { "name": "Asim Kumar Rai", "department": "CSE" },
  { "name": "Piyoush Kumar", "department": "CSE" },
  { "name": "Rinki Singh", "department": "CSE" },
  { "name": "Aditya Batra", "department": "CSE" },
  { "name": "Sakshi Garg", "department": "CSE" },
  { "name": "Arvind Kumar Tomer", "department": "CSE" },
  { "name": "Deepak Nagar", "department": "CSE" },
  { "name": "Prafull Goswami", "department": "CSE" },
  { "name": "Manjula Shukla", "department": "CSE" },
  { "name": "Neha Rani", "department": "CSE" },
  { "name": "Gaurav Gulati", "department": "CSE" },
  { "name": "Vandna Tomar", "department": "CSE" },
  { "name": "Swati Singh", "department": "CSE" },

  { "name": "Kunvar Dharmendra Vikram Singh", "department": "CSD" },

  { "name": "Siddhi Nath Rajan", "department": "IT" },
  { "name": "Ram Krishna Singh", "department": "IT" },
  { "name": "Neeraj Kumar Sirohi", "department": "IT" },
  { "name": "Bhanu Verma", "department": "IT" },
  { "name": "Manish Kumar Singh", "department": "IT" },
  { "name": "Monalisa Panigrahi", "department": "IT" },
  { "name": "Manoj Kumar Chaurasiya", "department": "IT" },
  { "name": "Raj Gopal Mishra", "department": "IT" },
  { "name": "Ayush Kumar Sharma", "department": "IT" },
  { "name": "Nidhi Sharma", "department": "IT" },
  { "name": "Seema Kumari", "department": "IT" },
  { "name": "Yousuf Haider", "department": "IT" },
  { "name": "Renu Prasad", "department": "IT" },
  { "name": "Megha Jha", "department": "IT" },

  { "name": "Priyanka Bhardwaj", "department": "ECE" },
  { "name": "Radha Raman Pandey", "department": "ECE" },
  { "name": "Vijay Kumar", "department": "ECE" },
  { "name": "Balwant Singh", "department": "ECE" },
  { "name": "Jyoti Guglani", "department": "ECE" },
  { "name": "Atul Kumar Kushwaha", "department": "ECE" },
  { "name": "Mayurika Saxena", "department": "ECE" },
  { "name": "V. K. Agrawal", "department": "ECE" },
  { "name": "Ajay Kumar", "department": "ECE" },
  { "name": "Pushpender", "department": "ECE" },
  { "name": "Sanjeev Sharma", "department": "ECE" },
  { "name": "Jyoshita", "department": "ECE" },
  { "name": "Gunjan Bhargava", "department": "ECE" },
  { "name": "Ajay Singh", "department": "ECE" },

  { "name": "Vivek Pandey", "department": "ME" },
  { "name": "Krishna Vijay Ojha", "department": "ME" },
  { "name": "Suraj Choudhary", "department": "ME" },
  { "name": "Subhash Mishra", "department": "ME" },
  { "name": "Ankit Aggarwal", "department": "ME" },
  { "name": "Manish Kumar", "department": "ME" },
  { "name": "Vivek Gupta", "department": "ME" },
  { "name": "Dinesh Kumar Kushwaha", "department": "ME" },
  { "name": "Surender Kumar", "department": "ME" },
  { "name": "Saurabh Kumar", "department": "ME" },
  { "name": "Anuj Kumar", "department": "ME" },

  { "name": "Mahendra Pratap Singh", "department": "MBA" },
  { "name": "Siby James", "department": "MBA" },
  { "name": "Nitin Mohan", "department": "MBA" },
  { "name": "Kavita Singh", "department": "MBA" },
  { "name": "Riyazuddin", "department": "MBA" },
  { "name": "Sapna Kumari", "department": "MBA" },
  { "name": "Richa Sardana", "department": "MBA" },
  { "name": "Subha Bhasin", "department": "MBA" },
  { "name": "Anurag Agarwal", "department": "MBA" },
  { "name": "Pratibha Pandey", "department": "MBA" },
  { "name": "Shachi Pathak", "department": "MBA" },
  { "name": "Pallavi Singh", "department": "MBA" },

  { "name": "Kavita Saxena", "department": "MCA" },
  { "name": "Ashish Pandey", "department": "MCA" },
  { "name": "Nikhil Gupta", "department": "MCA" },
  { "name": "Varun Chaudhary", "department": "MCA" },
  { "name": "Sonia Sharma", "department": "MCA" },
  { "name": "Vipin Kumar Sharma", "department": "MCA" },
  { "name": "Nikhilendra", "department": "MCA" },
  { "name": "Nakul Rana", "department": "MCA" }
]
